metrognome/__init__.py
metrognome/audio_manager.py
metrognome/main.py
metrognome/metrognome_logic.py
metrognome/metrognome_window.py
metrognome/resources/beep.wav
metrognome/resources/click.wav
metrognome/resources/icon.svg
metrognome/resources/kick.wav
metrognome/resources/snare.wav
MetroGnome-1.0.0.dist-info/METADATA
MetroGnome-1.0.0.dist-info/WHEEL
MetroGnome-1.0.0.dist-info/entry_points.txt
MetroGnome-1.0.0.dist-info/top_level.txt
MetroGnome-1.0.0.dist-info/RECORD
