Metadata-Version: 2.1
Name: MetroGnome
Version: 1.0.0
Summary: A cross-platform metronome using PyQt6
Author-email: David Baucum <david@baucum.me>
Maintainer-email: David Baucum <david@baucum.me>
License: GPLv3
Project-URL: homepage, https://gitlab.com/maxolasersquad/metrognome
Project-URL: documentation, https://gitlab.com/maxolasersquad/metrognome/-/blob/main/README.md
Project-URL: source, https://gitlab.com/maxolasersquad/metrognome
Project-URL: issues, https://gitlab.com/maxolasersquad/metrognome/-/issues
Project-URL: changelog, https://gitlab.com/maxolasersquad/metrognome/-/releases
Keywords: metronome
Requires-Python: >=3.12
Requires-Dist: PyQt6==6.7.1
Requires-Dist: PyQt6-Qt6==6.7.3
